{
  "parent": "minecraft:block/block",
  "textures": {
    "particle": "minecraft:block/dirt",
    "bottom": "minecraft:block/dirt",
    "top_base": "minecraft:block/dirt",
    "top_overlay": "themod:block/worn_grass_light_overlay",
    "side": "minecraft:block/grass_block_side",
    "side_overlay": "minecraft:block/grass_block_side_overlay"
  },
  "elements": [
    {
      "from": [0, 0, 0],
      "to": [16, 16, 16],
      "faces": {
        "down": {"uv": [0, 0, 16, 16], "texture": "#bottom", "cullface": "down"},
        "up": {"uv": [0, 0, 16, 16], "texture": "#top_base", "cullface": "up"},
        "north": {"uv": [0, 0, 16, 16], "texture": "#side", "cullface": "north"},
        "south": {"uv": [0, 0, 16, 16], "texture": "#side", "cullface": "south"},
        "west": {"uv": [0, 0, 16, 16], "texture": "#side", "cullface": "west"},
        "east": {"uv": [0, 0, 16, 16], "texture": "#side", "cullface": "east"}
      }
    },
    {
      "from": [0, 16.01, 0],
      "to": [16, 16.01, 16],
      "faces": {
        "up": {"uv": [0, 0, 16, 16], "texture": "#top_overlay", "tintindex": 0}
      }
    },
    {
      "from": [0, 0, 0],
      "to": [16, 16, 16],
      "faces": {
        "north": {"uv": [0, 0, 16, 16], "texture": "#side_overlay", "tintindex": 0, "cullface": "north"},
        "south": {"uv": [0, 0, 16, 16], "texture": "#side_overlay", "tintindex": 0, "cullface": "south"},
        "west": {"uv": [0, 0, 16, 16], "texture": "#side_overlay", "tintindex": 0, "cullface": "west"},
        "east": {"uv": [0, 0, 16, 16], "texture": "#side_overlay", "tintindex": 0, "cullface": "east"}
      }
    }
  ]
}
